verse/content/audio/__init__.py
verse/content/audio/_models.py
verse/content/audio/component.py
verse/content/audio/providers/av.py
verse/content/audio/providers/default.py
verse/content/audio/py.typed
verse/content/image/__init__.py
verse/content/image/_models.py
verse/content/image/component.py
verse/content/image/providers/default.py
verse/content/image/providers/pillow.py
verse/content/image/py.typed
verse/content/live_stream/__init__.py
verse/content/live_stream/_models.py
verse/content/live_stream/component.py
verse/content/live_stream/providers/av.py
verse/content/live_stream/providers/default.py
verse/content/live_stream/py.typed
verse/content/video/__init__.py
verse/content/video/_models.py
verse/content/video/component.py
verse/content/video/providers/av.py
verse/content/video/providers/default.py
verse/content/video/py.typed
verse_content-0.0.21.dist-info/LICENSE
verse_content-0.0.21.dist-info/METADATA
verse_content-0.0.21.dist-info/WHEEL
verse_content-0.0.21.dist-info/RECORD
